tracker/__init__.py
tracker/app.py
tracker/dependency.py
tracker/env.py
tracker/core/__init__.py
tracker/core/fix_version_detection.py
tracker/core/git_push_hook.py
tracker/core/git_repo.py
tracker/core/connectors/__init__.py
tracker/core/connectors/issue_handler.py
tracker/core/connectors/webhook_parser.py
tracker/core/connectors/git/__init__.py
tracker/core/connectors/git/bitbucket.py
tracker/core/connectors/git/github.py
git_issue_tracker-0.1.1.dist-info/LICENSE
git_issue_tracker-0.1.1.dist-info/METADATA
git_issue_tracker-0.1.1.dist-info/WHEEL
git_issue_tracker-0.1.1.dist-info/top_level.txt
git_issue_tracker-0.1.1.dist-info/RECORD
