Metadata-Version: 2.1
Name: git-issue-tracker
Version: 0.1.1
Summary: Git issue tracker
Home-page: https://github.com/lexbel/git_issue_tracker
Author: Aleksandr Belyaev
Author-email: lexbel89@gmail.com
Classifier: Programming Language :: Python :: 3
Classifier: License :: OSI Approved :: MIT License
Classifier: Operating System :: OS Independent
Requires-Python: >=3.6
License-File: LICENSE
Requires-Dist: injector (==0.19.0)
Requires-Dist: Flask (==2.1.2)
Requires-Dist: Flask-Injector (==0.13.0)
Requires-Dist: GitPython (==3.1.2)
